colcon_package_of/__init__.py
colcon_package_of/verb/__init__.py
colcon_package_of/verb/package_of.py
colcon_package_of-0.0.1.dist-info/LICENSE
colcon_package_of-0.0.1.dist-info/METADATA
colcon_package_of-0.0.1.dist-info/WHEEL
colcon_package_of-0.0.1.dist-info/entry_points.txt
colcon_package_of-0.0.1.dist-info/top_level.txt
colcon_package_of-0.0.1.dist-info/zip-safe
colcon_package_of-0.0.1.dist-info/RECORD
