Metadata-Version: 2.1
Name: colcon-package-of
Version: 0.0.1
Summary: Extension for colcon to get packages of files.
Home-page: https://colcon.readthedocs.io
Author: Tim Perkins
Author-email: code@taughz.dev
License: Apache License, Version 2.0
Project-URL: Changelog, https://github.com/colcon/colcon-package-of/milestones?direction=desc&sort=due_date&state=closed
Project-URL: GitHub, https://github.com/colcon/colcon-package-of/
Keywords: colcon
Platform: UNKNOWN
Classifier: Development Status :: 3 - Alpha
Classifier: Environment :: Plugins
Classifier: Intended Audience :: Developers
Classifier: License :: OSI Approved :: Apache Software License
Classifier: Operating System :: MacOS
Classifier: Operating System :: POSIX
Classifier: Programming Language :: Python
Classifier: Topic :: Software Development :: Build Tools
Requires-Python: >=3.10
License-File: LICENSE
Requires-Dist: colcon-core
Provides-Extra: test
Requires-Dist: black>=24.8.0; extra == "test"
Requires-Dist: flake8-blind-except; extra == "test"
Requires-Dist: flake8-builtins; extra == "test"
Requires-Dist: flake8-class-newline; extra == "test"
Requires-Dist: flake8-comprehensions; extra == "test"
Requires-Dist: flake8-deprecated; extra == "test"
Requires-Dist: flake8-docstrings; extra == "test"
Requires-Dist: flake8-import-order; extra == "test"
Requires-Dist: flake8-quotes; extra == "test"
Requires-Dist: flake8<6,>=3.6.0; extra == "test"
Requires-Dist: pep8-naming; extra == "test"
Requires-Dist: pylint; extra == "test"
Requires-Dist: pytest; extra == "test"
Requires-Dist: pytest-cov; extra == "test"
Requires-Dist: scspell3k>=2.2; extra == "test"
